flagship/__init__.py
flagship/api_manager.py
flagship/bucketing_manager.py
flagship/cache_helper.py
flagship/cache_manager.py
flagship/campaign.py
flagship/config.py
flagship/config_manager.py
flagship/constants.py
flagship/decision_manager.py
flagship/decision_mode.py
flagship/decorators.py
flagship/errors.py
flagship/flag.py
flagship/flag_metadata.py
flagship/flagship_context.py
flagship/hits.py
flagship/http_helper.py
flagship/log_manager.py
flagship/modification.py
flagship/murmur32x86.py
flagship/status.py
flagship/status_listener.py
flagship/targeting.py
flagship/targeting_comparator.py
flagship/tracking_manager.py
flagship/utils.py
flagship/variation.py
flagship/variation_group.py
flagship/visitor.py
flagship/visitor_strategies.py
flagship-3.0.0.dist-info/LICENSE
flagship-3.0.0.dist-info/METADATA
flagship-3.0.0.dist-info/WHEEL
flagship-3.0.0.dist-info/RECORD
