Metadata-Version: 2.1
Name: flagship
Version: 3.0.0
Summary: Flagship Python SDK
License: Apache License Version 2.0
Author: Raphael
Author-email: raphael@abtasty.com
Requires-Python: >=3.7
Classifier: License :: Other/Proprietary License
Classifier: Programming Language :: Python :: 3
Classifier: Programming Language :: Python :: 3.7
Classifier: Programming Language :: Python :: 3.8
Classifier: Programming Language :: Python :: 3.9
Classifier: Programming Language :: Python :: 3.10
Classifier: Programming Language :: Python :: 3.11
Classifier: Programming Language :: Python :: 3.12
Requires-Dist: importlib-metadata (>=6.0.0)
Requires-Dist: mock (>=5.1.0)
Requires-Dist: pytest (>=7.4.3)
Requires-Dist: pytest-cov (>=4.1.0,<5.0.0)
Requires-Dist: requests (>=2.31.0)
Requires-Dist: responses (==0.23.0)
Requires-Dist: tomli-w (>=1.0.0,<2.0.0)
Requires-Dist: urllib3 (==1.26.18)
Requires-Dist: zipp (>=3.12.0)
Project-URL: Documentation, https://docs.developers.flagship.io/docs/python
Project-URL: Sources, https://github.com/abtasty/flagship-python-sdk
